HoloMem/HoloMem.py
HoloMem/__init__.py
holomem-0.1.0.dist-info/METADATA
holomem-0.1.0.dist-info/WHEEL
holomem-0.1.0.dist-info/top_level.txt
holomem-0.1.0.dist-info/RECORD
