Metadata-Version: 2.4
Name: HoloMem
Version: 0.1.0
Summary: A Modern 4-Stage Synthetic Memory
Author: Tristan McBride Sr.
Author-email: "Tristan McBride Sr." <142635792+TristanMcBrideSr@users.noreply.github.com>
Maintainer-email: "Tristan McBride Sr." <142635792+TristanMcBrideSr@users.noreply.github.com>
License-Expression: Apache-2.0
Project-URL: Homepage, https://github.com/TristanMcBrideSr
Keywords: AI,Agents,Memory,Productivity,Automation,Voice Assistant,Chatbot,LLM,Large Language Model
Classifier: Programming Language :: Python :: 3
Classifier: Operating System :: OS Independent
Classifier: Intended Audience :: Developers
Requires-Python: >=3.10
Requires-Dist: Pillow
Requires-Dist: rapidfuzz
Requires-Dist: numpy
Requires-Dist: SynMem
Dynamic: author
